{
  "stories": [
    {
      "id": 1,
      "user": "luisferdk",
      "img": "/images/stories/luisferdk.jpg"
    },
    {
      "id": 2,
      "user": "nney09",
      "img": "/images/stories/nney09.jpg"
    },
    {
      "id": 3,
      "user": "alejofive",
      "img": "/images/stories/alejofive.jpg"
    }
  ],
  "posts": [
    {
      "id": 1,
      "user": "alejofive",
      "caption": "I'm ready",
      "imgUser": "/images/stories/alejofive.jpg",
      "imgPost": "/images/posts/alejofive.jpg",
      "likes": {
        "number": 3,
        "lastUser": "John",
        "images": [
          "/images/stories/luisferdk.jpg"
        ]
      },
      "comments": [
        {
          "user": "nney09",
          "description": "Que buena foto"
        },
        {
          "user": "luisferdk",
          "description": "Brutal. Súper Gamer"
        }
      ],
      "time": "Hace 10 horas"
    },
    {
      "id": 2,
      "user": "luisferdk",
      "caption": "La vida es duro para algunos, otros solo disfrutamos",
      "imgUser": "/images/stories/luisferdk.jpg",
      "imgPost": "/images/posts/luisferdk.jpg",
      "likes": {
        "number": 35,
        "lastUser": "nney09",
        "images": [
          "/images/stories/alejofive.jpg",
          "/images/stories/nney09.jpg"
        ]
      },
      "comments": [
        {
          "user": "nney09",
          "description": "Me encanta esa foto Mi Vida"
        }
      ],
      "time": "Hace 5 horas"
    },
    {
      "id": 3,
      "user": "nney09",
      "caption": "Aquí les comparto un poco de mi día a día",
      "imgUser": "/images/stories/nney09.jpg",
      "imgPost": "/images/posts/ney.jpg",
      "likes": {
        "number": 50,
        "lastUser": "luisferdk",
        "images": [
          "/images/stories/luisferdk.jpg",
          "/images/stories/alejofive.jpg"
        ]
      },
      "comments": [
        {
          "user": "luisferdk",
          "description": "Esooo pantallera UI/UX"
        },
        {
          "user": "alejofive",
          "description": "Que linda Ney te extraño"
        }
      ],
      "time": "Hace un momento"
    }
  ]
}